setup.py
rem/__init__.py
rem.egg-info/PKG-INFO
rem.egg-info/SOURCES.txt
rem.egg-info/dependency_links.txt
rem.egg-info/entry_points.txt
rem.egg-info/requires.txt
rem.egg-info/top_level.txt