Metadata-Version: 1.1
Name: rem
Version: 1.0.2
Summary: Set reminders blazing fast.
Home-page: http://github.com/Genki-S/rem/
Author: Genki Sugimoto
Author-email: cfhoyuk.reccos.nelg@gmail.com
License: MIT
Download-URL: https://pypi.python.org/pypi/rem/
Platform: UNKNOWN
